feedback/__init__.py
feedback/apps.py
feedback/feedback.py
feedback/utils.py
feedback/extensions/__init__.py
feedback/extensions/filters.py
feedback/public/default_icons/aface1.png
feedback/public/default_icons/aface2.png
feedback/public/default_icons/aface3.png
feedback/public/default_icons/aface4.png
feedback/public/default_icons/aface5.png
feedback/public/default_icons/amidface1.png
feedback/public/default_icons/amidface2.png
feedback/public/default_icons/amidface3.png
feedback/public/default_icons/amidface4.png
feedback/public/default_icons/amidface5.png
feedback/public/default_icons/anum1.png
feedback/public/default_icons/anum2.png
feedback/public/default_icons/anum3.png
feedback/public/default_icons/anum4.png
feedback/public/default_icons/anum5.png
feedback/public/default_icons/astar1.png
feedback/public/default_icons/astar2.png
feedback/public/default_icons/astar3.png
feedback/public/default_icons/astar4.png
feedback/public/default_icons/astar5.png
feedback/public/default_icons/iface1.png
feedback/public/default_icons/iface2.png
feedback/public/default_icons/iface3.png
feedback/public/default_icons/iface4.png
feedback/public/default_icons/iface5.png
feedback/public/default_icons/imidface1.png
feedback/public/default_icons/imidface2.png
feedback/public/default_icons/imidface3.png
feedback/public/default_icons/imidface4.png
feedback/public/default_icons/imidface5.png
feedback/public/default_icons/inum1.png
feedback/public/default_icons/inum2.png
feedback/public/default_icons/inum3.png
feedback/public/default_icons/inum4.png
feedback/public/default_icons/inum5.png
feedback/public/default_icons/istar1.png
feedback/public/default_icons/istar2.png
feedback/public/default_icons/istar3.png
feedback/public/default_icons/istar4.png
feedback/public/default_icons/istar5.png
feedback/settings/__init__.py
feedback/settings/common.py
feedback/settings/production.py
feedback/settings/test.py
feedback/static/README.txt
feedback/static/css/feedback.css
feedback_xblock-2.1.0.dist-info/LICENSE
feedback_xblock-2.1.0.dist-info/METADATA
feedback_xblock-2.1.0.dist-info/WHEEL
feedback_xblock-2.1.0.dist-info/entry_points.txt
feedback_xblock-2.1.0.dist-info/top_level.txt
feedback_xblock-2.1.0.dist-info/RECORD
