Metadata-Version: 2.1
Name: feedback-xblock
Version: 2.1.0
Summary: XBlock for providing feedback on course content
License-File: LICENSE
Requires-Dist: XBlock
